Workbook

Sheet Cover
B1: Bending Spoons: acquisition-integration model
B2: Outside-in, public sources only. As of Oct 12, 2026. Prepared by Jeff King.
B4: Question: how much does integration speed matter to Bending Spoons' economics, and what should finance own in each integration?
B6: Tabs
B7: Inputs: every hardcoded number, with its source. Change blue cells here; everything else recalculates.
B8: Leverage: net-debt walk from Q2 2026 through the IPO, Airtable and Miro, vs. the 4.0x covenant. Shows why documented cost savings matter.
B9: Miro_Payback: price / post-integration operating income across revenue-retention and margin cases; cost of each month of delay.
B10: Working_Capital: receivables and DSO check across acquisitions (order-to-cash lens).
B11: Scorecard: one-page integration scorecard template per acquisition (example row = Miro, illustrative targets).
B12: Lookback: 12-month underwritten-vs-actual template that feeds the next underwriting.
B13: Sources: links to every page used.
B15: Legend
... B21: Airtable and Miro EBITDA are not disclosed; their contributions are assumptions. Nothing here is investment advice.

Sheet Inputs
A1: Inputs ($ in millions unless noted)
A3: Item | B3: Value | C3: Unit | D3: Source | E3: Note
A4: Bending Spoons, Q2 2026 (quarter ended Jun 30, 2026)
A5: Q2 2026 revenue | B5: 704.155 | C5: $mm | D5: Q2 2026 earnings release (Aug 13, 2026) | E5: Income statement
A6: Q2 2026 Adjusted Operating Income | B6: 381.149 | C6: $mm | D6: Q2 2026 earnings release (Aug 13, 2026) | E6: Non-GAAP reconciliation
A7: Q2 2026 interest expense | B7: 108.97 | C7: $mm | D7: Q2 2026 earnings release (Aug 13, 2026) | E7: Income statement
A8: Q2 2026 reorganization-related expense | B8: 50.799 | C8: $mm | D8: Q2 2026 earnings release (Aug 13, 2026) | E8: Mostly separation packages at AOL, Eventbrite, Tractive, Vimeo
A9: Q2 2026 organic revenue growth | B9: 0.03 | C9: % | D9: Q2 2026 earnings release (Aug 13, 2026) | E9: Headline growth was 126%
A10: Net debt, Jun 30, 2026 | B10: 4090 | C10: $mm | D10: Q2 2026 earnings release (Aug 13, 2026) | E10: Long-term debt $4.88B less cash $793M
A11: Reported leverage ratio, Jun 30, 2026 | B11: 2.4 | C11: x | D11: Q2 2026 earnings release (Aug 13, 2026) | E11: Net debt / TTM pro forma adj. EBITDA incl. achieved + certain expected savings (footnote 3)
A12: Cash and cash equivalents, Jun 30, 2026 | B12: 792.95 | C12: $mm | D12: Q2 2026 earnings release (Aug 13, 2026) | E12: Balance sheet
A13: Debt maturing within 12 months | B13: 794 | C13: $mm | D13: Q2 2026 earnings release (Aug 13, 2026) | E13: Long-term debt, current
A14: Undrawn revolver capacity | B14: 1280 | C14: $mm | D14: Q2 2026 earnings release (Aug 13, 2026) | E14: Of $1.58B total
A15: H1 2026 net cash from operating activities | B15: 254.24 | C15: $mm | D15: Q2 2026 earnings release (Aug 13, 2026) | E15: After $161M interest paid
A16: H1 2026 capex (PP&E) | B16: 3.969 | C16: $mm | D16: Q2 2026 earnings release (Aug 13, 2026) | E16: Cash flow statement
... A22: FY2026 Adjusted Operating Income guidance, high | B22: 1510 | C22: $mm | D22: Q2 2026 earnings release (Aug 13, 2026) | E22: Excludes Airtable
A23: Post-quarter events
A24: IPO net proceeds (July 2026) | B24: 1100 | C24: $mm | D24: Q2 2026 earnings release (Aug 13, 2026) | E24: 39.6M primary shares at $29; assumed held as cash, reducing net debt
A25: Airtable enterprise value (closed Sep 4, 2026) | B25: 1290 | C25: $mm | D25: Q2 2026 earnings release (Aug 13, 2026) | E25: All cash; EV basis so net debt rises by EV
A26: Miro enterprise value (signed Sep 10, 2026; close Q4) | B26: 1355 | C26: $mm | D26: https://investors.bendingspoons.com/newsroom/bending-spoons-agrees-to-acquire-miro | E26: Equity value ~$1.79B incl. Miro net cash
A27: Miro sellers reinvesting in new BSP equity | B27: 295 | C27: $mm | D27: https://investors.bendingspoons.com/newsroom/bending-spoons-agrees-to-acquire-miro | E27: Reduces cash funding need
A28: Miro ARR | B28: 600 | C28: $mm | D28: https://investors.bendingspoons.com/newsroom/bending-spoons-agrees-to-acquire-miro | E28: 'About $600 million'; ~90% business/enterprise
A29: Leverage covenant (net debt / adj. EBITDA) | B29: 4 | C29: x | D29: https://thegoogly.substack.com/p/bending-spoons-the-comeback-story | E29: Secondary summary of prospectus; verify in filing
A30: Cost of incremental debt | B30: 0.0943 | C30: % | D30: https://thegoogly.substack.com/p/bending-spoons-the-comeback-story | E30: All-in rate on largest USD term loan; euro TLAs likely cheaper
A31: My assumptions (yellow; change these)
A32: H2 2026 free cash flow retained (debt paydown) | B32: 300 | C32: $mm | D32: Assumption | E32: H1 OCF less capex was ~$250M; H2 has a fuller AOI base
A33: Airtable pro forma EBITDA credited at year-end | B33: 0 | C33: $mm | D33: Assumption | E33: Not disclosed. Base case 0 = no credit until savings are documented
A34: Miro pro forma EBITDA credited at year-end | B34: 0 | C34: $mm | D34: Assumption | E34: Not disclosed. Base case 0
A35: Miro revenue retained after repricing (base) | B35: 0.92 | C35: % | D35: Assumption | E35: BSP group NRR was 91-95% in 2023-25 (secondary)
A36: Miro post-integration operating margin (base) | B36: 0.45 | C36: % | D36: Assumption | E36: Group adj. operating margin was 54% in Q2 2026

Sheet Leverage
A1: Net-debt and leverage walk, Jun 30, 2026 to pro forma year-end 2026 ($mm)
A2: Point: with zero EBITDA credit for Airtable and Miro, leverage stays under the covenant, but the headroom left for the next deal depends on how fast savings are achieved and documented.
A4: Line | B4: Value | C4: How it's built
A5: Net debt, Jun 30, 2026 | B5: =Inputs!$B$10 -> 4090 | C5: Reported
A6: Less: IPO net proceeds | B6: =-Inputs!$B$24 -> -1100 | C6: Assumes proceeds held as cash until deployed
A7: Less: H2 2026 free cash flow retained | B7: =-Inputs!$B$32 -> -300 | C7: Assumption
A8: Plus: Airtable (EV) | B8: =Inputs!$B$25 -> 1290 | C8: All cash, closed Sep 4, 2026
A9: Plus: Miro EV less seller rollover | B9: =Inputs!$B$26-Inputs!$B$27 -> 1060 | C9: Expected Q4 2026 close
A10: Pro forma net debt, year-end 2026 | B10: =SUM(B5:B9) -> 5040 | C10: Excludes Tractive $115M deferred consideration (May 2027) and deal fees
A12: Implied TTM adj. EBITDA, Jun 30, 2026 | B12: =Inputs!$B$10/Inputs!$B$11 -> 1704.1667 | C12: Net debt / reported 2.4x; held flat (conservative: ignores H2 growth in TTM)
A13: Plus: Airtable EBITDA credited | B13: =Inputs!$B$33 -> 0 | C13: Assumption
A14: Plus: Miro EBITDA credited | B14: =Inputs!$B$34 -> 0 | C14: Assumption
A15: Pro forma adj. EBITDA | B15: =SUM(B12:B14) -> 1704.1667
A17: Pro forma leverage | B17: =IFERROR(B10/B15,0) -> 2.9574572 | C17: Net debt / EBITDA
A18: Covenant | B18: =Inputs!$B$29 -> 4 | C18: Secondary source; verify
A19: Headroom to covenant | B19: =B18-B17 -> 1.0425428
A20: Debt capacity before covenant ($mm) | B20: =B18*B15-B10 -> 1776.6667 | C20: Extra net debt before hitting 4.0x
A22: Interest on Miro funding, annual ($mm) | B22: =(Inputs!$B$26-Inputs!$B$27)*Inputs!$B$30 -> 99.958 | C22: Carry on the incremental debt at the cited 9.43% rate; runs from day one regardless of integration pace
A23: Q2 2026 interest as % of Adjusted Operating Income | B23: =Inputs!$B$7/Inputs!$B$6 -> 0.28589869 | C23: Reported Q2 figures
A26: Sensitivity: combined Airtable + Miro EBITDA credited ($mm) vs. pro forma leverage and capacity
A27: Combined EBITDA credited ($mm) | B27: Leverage | C27: Debt capacity to 4.0x ($mm)
A28: 0 | B28: =IFERROR($B$10/($B$12+A28),0) -> 2.9574572 | C28: =$B$18*($B$12+A28)-$B$10 -> 1776.6667
A29: 100 | B29: =IFERROR($B$10/($B$12+A29),0) -> 2.7935335 | C29: =$B$18*($B$12+A29)-$B$10 -> 2176.6667
A30: 200 | B30: =IFERROR($B$10/($B$12+A30),0) -> 2.6468271 | C30: =$B$18*($B$12+A30)-$B$10 -> 2576.6667
A31: 300 | B31: =IFERROR($B$10/($B$12+A31),0) -> 2.5147609 | C31: =$B$18*($B$12+A31)-$B$10 -> 2976.6667
A32: 400 | B32: =IFERROR($B$10/($B$12+A32),0) -> 2.3952475 | C32: =$B$18*($B$12+A32)-$B$10 -> 3376.6667
A33: 500 | B33: =IFERROR($B$10/($B$12+A33),0) -> 2.2865784 | C33: =$B$18*($B$12+A33)-$B$10 -> 3776.6667
A35: Reading: each $100M of documented savings credited adds about $400M of acquisition capacity at 4.0x. That is why finance's savings evidence is part of the deal engine, not bookkeeping.

Sheet Miro_Payback
A1: Miro: price / post-integration operating income
A2: Multiple = EV / (ARR x revenue retained x operating margin). Lower is better; ~5x = 20% annual pre-tax return on price.
A4: Miro EV ($mm) | B4: =Inputs!$B$26 -> 1355
A5: Miro ARR ($mm) | B5: =Inputs!$B$28 -> 600
A6: EV / ARR | B6: =B4/B5 -> 2.2583333
A8: Grid: rows = operating margin, columns = revenue retained
A9: Margin \ Retained | B9: 0.85 | C9: 0.92 | D9: 1
A10: 0.35 | B10: =IFERROR($B$4/($B$5*B$9*$A10),0) -> 7.5910364 | C10: =IFERROR($B$4/($B$5*C$9*$A10),0) -> 7.0134576 | D10: =IFERROR($B$4/($B$5*D$9*$A10),0) -> 6.452381
A11: 0.45 | B11: =IFERROR($B$4/($B$5*B$9*$A11),0) -> 5.9041394 | C11: =IFERROR($B$4/($B$5*C$9*$A11),0) -> 5.4549114 | D11: =IFERROR($B$4/($B$5*D$9*$A11),0) -> 5.0185185
A12: 0.55 | B12: =IFERROR($B$4/($B$5*B$9*$A12),0) -> 4.8306595 | C12: =IFERROR($B$4/($B$5*C$9*$A12),0) -> 4.4631094 | D12: =IFERROR($B$4/($B$5*D$9*$A12),0) -> 4.1060606
A15: Base case (from Inputs)
A16: Revenue retained | B16: =Inputs!$B$35 -> 0.92
A17: Operating margin | B17: =Inputs!$B$36 -> 0.45
A18: Run-rate operating income ($mm) | B18: =B5*B16*B17 -> 248.4
A19: EV / run-rate operating income | B19: =IFERROR(B4/B18,0) -> 5.4549114
A20: Pre-tax yield on EV | B20: =IFERROR(B18/B4,0) -> 0.18332103
A21: Annual interest on Miro funding ($mm) | B21: =Leverage!B22 -> 99.958
A22: Operating income / interest (coverage) | B22: =IFERROR(B18/B21,0) -> 2.4850437
A24: Cost of delay
A25: Operating income lost per month of delay ($mm) | B25: =B18/12 -> 20.7
A26: Plus interest carried per month ($mm) | B26: =B21/12 -> 8.3298333
A27: Acquisition capacity unlocked once savings are credited ($mm) | B27: =B18*Inputs!$B$29 -> 993.6 | F27: Run-rate operating income x 4.0x covenant; used as a proxy for EBITDA
A29: Risk note: Brightcove's revenue fell after acquisition (secondary sources). Retention, not margin, is the variable to watch; the look-back tab tracks it.

Sheet Working_Capital
A1: Receivables check: did AR grow faster than revenue as acquisitions landed?
A3: Metric | B3: Dec 31, 2025 | C3: Jun 30, 2026 | D3: Note
A4: Accounts receivable ($mm) | B4: =Inputs!$B$17 -> 144.593 | C4: =Inputs!$B$18 -> 278.767
A5: Quarter revenue ($mm) | B5: =(Inputs!$B$20-Inputs!$B$19)/2 -> 367.977 | C5: =Inputs!$B$5 -> 704.155 | D5: Q4 2025 approximated as half of H2 2025 (not disclosed separately)
A6: Days in quarter | B6: 92 | C6: 91
A7: DSO (AR / quarter revenue x days) | B7: =IFERROR(B4/B5*B6,0) -> 36.150509 | C7: =IFERROR(C4/C5*C6,0) -> 36.025871
A8: AR growth | C8: =C4/B4-1 -> 0.92794257
A9: Revenue growth (quarter vs quarter) | C9: =C5/B5-1 -> 0.91358427
A11: Reading: AR roughly doubled, but DSO is about flat, so collections kept pace with acquired revenue. The mix is shifting, though: advertising (AOL) and invoiced B2B (Vimeo, Airtable, Miro) carry real credit and collection risk that app-store revenue doesn't. That argues for bringing each target's AR aging, credit memos, and bad-debt reserve into the Day 1-30 integration checklist.

Sheet Scorecard
A1: Integration scorecard (one page per acquisition)
A2: Fill the yellow cells. Example below = Miro, with illustrative targets I would propose; actuals are blank until close.
A3: Acquisition | B3: Miro
A4: Close date | B4: Q4 2026 (expected)
A5: Owner (finance) | B5: Jeff King
A7: Metric | B7: Target | C7: Actual | D7: Variance | E7: Status | F7: Why it matters
A8: Days to cash control (payouts on Juno) | B8: 30 | D8: =IF(C8="","",C8-B8) | E8: =IF(C8="","Open",IF(C8<=B8,"On track","Behind")) -> Open | F8: Cash is the first thing that can leak; 75% of revenue is electronic payments
A9: Days to first consolidated close | B9: 60 | D9: =IF(C9="","",C9-B9) | E9: =IF(C9="","Open",IF(C9<=B9,"On track","Behind")) -> Open | F9: Fixed external deadlines; the disclosed material weakness covers acquired-company integration
A10: Access removed same day as exits (%) | B10: 1 | D10: =IF(C10="","",C10-B10) | E10: =IF(C10="","Open",IF(C10>=B10,"On track","Behind")) -> Open | F10: Segregation of duties breaks first in deep reorganizations (Galf)
A11: Run-rate savings achieved vs. plan (%) | B11: 1 | D11: =IF(C11="","",C11-B11) | E11: =IF(C11="","Open",IF(C11>=B11,"On track","Behind")) -> Open | F11: Achieved savings are credited in reported leverage
A12: Net revenue retention vs. pre-deal (pp) | B12: 0 | D12: =IF(C12="","",C12-B12) | E12: =IF(C12="","Open",IF(C12>=B12,"On track","Behind")) -> Open | F12: Brightcove lesson: margin up, revenue down
A13: Reorganization spend vs. budget (%) | B13: 1 | D13: =IF(C13="","",C13-B13) | E13: =IF(C13="","Open",IF(C13<=B13,"On track","Behind")) -> Open | F13: Add-backs must reconcile to a cost center to survive audit
A14: Target systems retired (of total) | B14: 1 | D14: =IF(C14="","",C14-B14) | E14: =IF(C14="","Open",IF(C14>=B14,"On track","Behind")) -> Open | F14: Simplification: every legacy system kept is a control to test
A16: Sunset list (fill per deal)
A17: Item to retire | B17: Type | C17: Target date | D17: Done? | F17: Note
A18: Target's ERP / GL | B18: System | F18: Migrate to BSP chart of accounts at first close
A19: Target's billing/payment processors | B19: System | F19: Repoint payouts to Juno
A20: Target bank accounts | B20: Treasury | F20: Sweep, then close
A21: Redundant legal entities | B21: Entity | F21: Coordinate with tax (Italy transfer step)
A22: Target's board/management reporting packs | B22: Report | F22: Replace with BSP standard pack

Sheet Lookback
A1: 12-month look-back: underwritten vs. actual
A2: Run 12 months after close. The variances feed the next deal's underwriting assumptions. Example = Miro, underwritten values from the base case.
A4: Assumption | B4: Underwritten | C4: Actual (12 mo) | D4: Variance | E4: What changes in the next underwriting
A5: Revenue retained | B5: =Inputs!$B$35 -> 0.92 | D5: =IF(OR(B5="",C5=""),"",C5-B5)
A6: Operating margin | B6: =Inputs!$B$36 -> 0.45 | D6: =IF(OR(B6="",C6=""),"",C6-B6)
A7: Run-rate operating income ($mm) | B7: =Miro_Payback!B18 -> 248.4 | D7: =IF(OR(B7="",C7=""),"",C7-B7)
A8: Reorganization cost ($mm) | D8: =IF(OR(B8="",C8=""),"",C8-B8)
A9: Months to run-rate savings | D9: =IF(OR(B9="",C9=""),"",C9-B9)
A10: Days to first consolidated close | B10: =Scorecard!B9 -> 60 | D10: =IF(OR(B10="",C10=""),"",C10-B10)
A12: Tie-in: Bending Spoons' Minerva system predicts user lifetime value. The retained-revenue line should be checked against Minerva's cohort curves, not a separate spreadsheet.

Sheet Sources
A1: Sources (opened Oct 12, 2026)
A3: Source | B3: URL
A4: Bending Spoons Q2 2026 earnings release (primary) | B4: https://bendingspoons.com/documents/financials/2026/20260813%20Bending%20Spoons%E2%80%94Q2%202026%20Results.pdf
A5: Bending Spoons: agreement to acquire Miro (primary) | B5: https://investors.bendingspoons.com/newsroom/bending-spoons-agrees-to-acquire-miro
A6: Bending Spoons: completes acquisition of Airtable (primary) | B6: https://investors.bendingspoons.com/newsroom/bending-spoons-completes-acquisition-of-airtable
A7: The Googly: prospectus analysis (secondary; covenant, debt rate, material weaknesses) | B7: https://thegoogly.substack.com/p/bending-spoons-the-comeback-story
A8: Mostly Metrics: S-1 breakdown (secondary; FY2025 revenue, NRR) | B8: https://www.mostlymetrics.com/p/bending-spoons-ipo-s1-breakdown
